{
  "frames": {
    "cloud3.png": {
      "frame": {
        "x": 0,
        "y": 0,
        "w": 56,
        "h": 46
      },
      "rotated": false,
      "trimmed": true,
      "spriteSourceSize": {
        "x": 2,
        "y": 7,
        "w": 56,
        "h": 46
      },
      "sourceSize": {
        "w": 64,
        "h": 64
      },
      "pivot": {
        "x": 0.5,
        "y": 0.5
      }
    },
    "cloud1.png": {
      "frame": {
        "x": 56,
        "y": 0,
        "w": 53,
        "h": 31
      },
      "rotated": false,
      "trimmed": true,
      "spriteSourceSize": {
        "x": 5,
        "y": 1,
        "w": 53,
        "h": 31
      },
      "sourceSize": {
        "w": 64,
        "h": 32
      },
      "pivot": {
        "x": 0.5,
        "y": 0.5
      }
    },
    "cloud2.png": {
      "frame": {
        "x": 109,
        "y": 0,
        "w": 31,
        "h": 13
      },
      "rotated": false,
      "trimmed": true,
      "spriteSourceSize": {
        "x": 0,
        "y": 10,
        "w": 31,
        "h": 13
      },
      "sourceSize": {
        "w": 32,
        "h": 32
      },
      "pivot": {
        "x": 0.5,
        "y": 0.5
      }
    }
  },
  "meta": {
    "app": "http://free-tex-packer.com",
    "version": "0.6.7",
    "image": "cloud-atlas.png",
    "format": "RGBA8888",
    "size": {
      "w": 140,
      "h": 46
    },
    "scale": 1
  }
}